{"parse":{"title":"removeCuratorEditableObjects","pageid":14853,"parsetree":{"*":"<root><template><title>RV</title><part><name>type</name>=<value>command\n\n</value></part><part><name>game1</name>=<value> arma3\n\n</value></part><part><name>version1</name>=<value> 1.16\n\n</value></part><part><name>serverExec</name>=<value> server\n\n</value></part><part><name>gr1</name>=<value> Curator\n\n</value></part><part><name>descr</name>=<value> Unregister objects which can be edited by a curator.\n\n</value></part><part><name>s1</name>=<value> curatorObj [[removeCuratorEditableObjects]] <ext><name>nowiki</name><attr/><inner>[[</inner><close>&lt;/nowiki&gt;</close></ext>objects], removeCrew]\n\n</value></part><part><name>p1</name>=<value> curatorObj: [[Object]] - Curator module\n\n</value></part><part><name>p2</name>=<value> objects: [[Array]]\n\n</value></part><part><name>p3</name>=<value> removeCrew: [[Boolean]]\n\n</value></part><part><name>r1</name>=<value> [[Nothing]]\n\n</value></part><part><name>x1</name>=<value> &lt;code&gt;curatorModule [[removeCuratorEditableObjects]] <ext><name>nowiki</name><attr/><inner>[[</inner><close>&lt;/nowiki&gt;</close></ext>[[cursorTarget]]], [[true]]]&lt;/code&gt;\n\n</value></part><part><name>seealso</name>=<value> [[Arma 3: Curator]], [[addCuratorEditableObjects]], [[curatorEditableObjects]]\n</value></part></template></root>"}}}