{"parse":{"title":"splitString","pageid":17371,"parsetree":{"*":"<root><template><title>RV</title><part><name>type</name>=<value>command\n\n</value></part><part><name index=\"1\"/><value> arma3\n\n</value></part><part><name index=\"2\"/><value>1.50\n\n</value></part><part><name>gr1</name>=<value> Strings\n\n</value></part><part><name index=\"3\"/><value> An SQF version of C++ [http://www.cplusplus.com/reference/cstring/strtok/ strtok]. Splits given ANSI string ''str'' into an array of tokens according to given ''delimiters''. In addition, if empty string \"\" is used for ''delimiters'', ''str'' is split by each character. If Unicode support is desired, see [[forceUnicode]].\n\n</value></part><part><name index=\"4\"/><value> str '''splitString''' delimiters\n\n</value></part><part><name>p1</name>=<value> str: [[String]] - A string to split\n</value></part><part><name>p2</name>=<value> delimiters: [[String]] - one or more characters, each used as a separate delimiter.\n</value></part><part><name index=\"5\"/><value> [[Array]]\n\n</value></part><part><name>x1</name>=<value> &lt;code&gt;_str = \"- This, is a sample string.\" [[splitString]] \"-,. \"; // [\"This\",\"is\",\"a\",\"sample\",\"string\"]\n_str [[joinString]] \" \"; // \"This is a sample string\"&lt;/code&gt;\n\n</value></part><part><name>x2</name>=<value> &lt;code&gt;\"\\A3\\ui_f\\data\\map\\vehicleicons\\iconLogic_ca.paa\" [[splitString]] \"\\.\"; \n// [\"A3\",\"ui_f\",\"data\",\"map\",\"vehicleicons\",\"iconLogic_ca\",\"paa\"]&lt;/code&gt;\n\n</value></part><part><name>x3</name>=<value> &lt;code&gt;\"1:2:3\" [[splitString]] \":\"; // [\"1\",\"2\",\"3\"]&lt;/code&gt;\n\n</value></part><part><name>x4</name>=<value> &lt;code&gt;\"Japa is the best!\" [[splitString]] \"\" [[joinString]] \" \"; // \"J a p a   i s   t h e   b e s t !\"&lt;/code&gt;\n\n</value></part><part><name>x5</name>=<value> &lt;code&gt;_cmd = [[currentMagazineDetail]] [[player]]; //\"9mm 16Rnd Mag(13/16)[id/cr:10000011/0]\"\n_cmd [[splitString]] \"([ ]/:)\"; //[\"9mm\",\"16Rnd\",\"Mag\",\"13\",\"16\",\"id\",\"cr\",\"10000011\",\"0\"]&lt;/code&gt;\n\n</value></part><part><name>x7</name>=<value> Remove all \\r\\n from file:&lt;code&gt;[[loadFile]] \"somefile.txt\" [[splitString]] [[toString]] [13,10] [[joinString]] \" \"&lt;/code&gt;\n\n</value></part><part><name index=\"6\"/><value> [[joinString]], [[set]], [[resize]], [[reverse]], [[select]], [[in]], [[find]], [[toArray]], [[forEach]], [[count]], [[deleteAt]], [[deleteRange]], [[append]], [[sort]], [[param]], [[params]], [[arrayIntersect]], [[toString]], [[endl]], [[forceUnicode]], [http://www.utf8-chartable.de/ Unicode Character Table]\n</value></part></template>\n\n[[Category:Scripting Commands|<template><title>uc:<template><title>PAGENAME</title></template></title></template>]]\n<template lineStart=\"1\"><title>GameCategory</title><part><name index=\"1\"/><value>arma3</value></part><part><name index=\"2\"/><value>Scripting Commands</value></part></template>\n\n<comment>&lt;!-- CONTINUE Notes --&gt;\n</comment>&lt;dl class=\"command_description\"&gt;\n&lt;dd class=\"notedate\"&gt;Posted on May 17, 2016 - 14:18 (UTC)&lt;/dd&gt;\n&lt;dt class=\"note\"&gt;[[User:BaerMitUmlaut|BaerMitUmlaut]]&lt;/dt&gt;\n&lt;dd class=\"note\"&gt;\nThis command is unreliable/broken when it comes to some non-ASCII characters (as of Arma 3 1.58):\n&lt;code&gt;\"M\u00f6rser\" splitString \"\"\n-&gt; [\"M\",\" \",\" \",\"r\",\"s\",\"e\",\"r\"]\n\"M\u00f6rser\" splitString \"\u00f6\"\n-&gt; [\"M\",\"rser\"]\n\"M\u00f6rser\" splitString \"\u00e4\"\n-&gt; [\"M\",\" rser\"]&lt;/code&gt;\n&lt;/dd&gt;\n\n&lt;dd class=\"notedate\"&gt;Posted on October 17, 2016 - 14:03 (UTC)&lt;/dd&gt;\n&lt;dt class=\"note\"&gt;[[User:Killzone Kid|Killzone Kid]]&lt;/dt&gt;\n&lt;dd class=\"note\"&gt; This commands works only with ASCII chars, any chars with codes &gt; 127, also used in different languages, will be converted to [\" \", \" \"]. Use [[toArray]] to preserve special characters:\n&lt;code&gt;_spaced = [[toArray]] \"M\u00f6rser\" [[apply]] {[[toString]] [_x]} [[joinString]] \" \"; // M \u00f6 r s e r&lt;/code&gt;\n&lt;/dd&gt;\n\n&lt;dd class=\"notedate\"&gt;Posted on July 19, 2019 - 11:17 (UTC)&lt;/dd&gt;\n&lt;dt class=\"note\"&gt;[[User:R3vo|R3vo]]&lt;/dt&gt;\n&lt;dd class=\"note\"&gt;\nWhen working with string which contain linebreaks...\n&lt;code&gt;\"stringWith\" + [[endl]] + \"Linebreak\" [[splitString]] \",; \"; //Result [\"someStringWith\nLinebreak\"]&lt;/code&gt;\n\n...one can remove those by adding [[endl]] as delimiter\n&lt;code&gt;\"stringWith\" + [[endl]] + \"Linebreak\" [[splitString]] \",; \" + [[endl]] //Result [\"someStringWith\",\"Linebreak\"]&lt;/code&gt;\n&lt;/dd&gt;\n&lt;/dl&gt;\n<comment>&lt;!-- DISCONTINUE Notes --&gt;</comment></root>"}}}