{"parse":{"title":"lnbSetPictureColorSelected","pageid":27181,"parsetree":{"*":"<root><template><title>Command\n\n</title><part><name>game1</name>=<value> arma3 </value></part><part><name>Game name</name>=<value>\n\n</value></part><part><name>version</name>=<value> 1 </value></part><part><name>Game version</name>=<value>\n\n</value></part><part><name>gr1</name>=<value> GUI Control - ListNBox </value></part><part><name>GROUP1</name>=<value>\n____________________________________________________________________________________________\n\n</value></part><part><name>descr</name>=<value> Sets the cell picture's colour on cell selection. </value></part><part><name>Description</name>=<value>\n\n</value></part><part><name>s1</name>=<value> [[lnbSetPictureColorSelected]] [idc, [row, column], colour] </value></part><part><name>Syntax</name>=<value>\n\n</value></part><part><name>p1</name>=<value> idc: [[Number]] </value></part><part><name>Parameter 1</name>=<value>\n\n</value></part><part><name>p2</name>=<value> row: [[Number]] - 0-based index (first row is 0, second is 1, etc) </value></part><part><name>Parameter 2</name>=<value>\n\n</value></part><part><name>p3</name>=<value> column: [[Number]] - 0-based index (first column is 0, second is 1, etc) </value></part><part><name>Parameter 3</name>=<value>\n\n</value></part><part><name>p4</name>=<value> colour: [[Color|Color (RGBA)]] </value></part><part><name>Parameter 4</name>=<value>\n____________________________________________________________________________________________\n\n</value></part><part><name>s2</name>=<value> ctrl [[lnbSetPictureColorSelected]] [<ext><name>nowiki</name><attr/></ext>[row, column], colour] </value></part><part><name>Alternative Syntax</name>=<value>\n\n</value></part><part><name>p21</name>=<value> ctrl: [[Control]] </value></part><part><name>Parameter 21</name>=<value>\n\n</value></part><part><name>p22</name>=<value> row: [[Number]] - 0-based index (first row is 0, second is 1, etc) </value></part><part><name>Parameter 22</name>=<value>\n\n</value></part><part><name>p23</name>=<value> column: [[Number]] - 0-based index (first column is 0, second is 1, etc) </value></part><part><name>Parameter 23</name>=<value>\n\n</value></part><part><name>p24</name>=<value> colour: [[Color|Color (RGBA)]] </value></part><part><name>Parameter 24</name>=<value>\n____________________________________________________________________________________________\n\n</value></part><part><name>x1</name>=<value> &lt;code&gt;[[lnbSetPictureColorSelected]] [1492, [1,0], [0,0.75,0.3,0.5]];&lt;/code&gt; </value></part><part><name>Example 1</name>=<value>\n\n</value></part><part><name>x2</name>=<value> &lt;code&gt;ctrl [[lnbSetPictureColorSelected]] [[0, 3], [1,0,0,1]];&lt;/code&gt; </value></part><part><name>Example 2</name>=<value>\n____________________________________________________________________________________________\n\n</value></part><part><name>seealso</name>=<value> [[lnbSetPictureColor]] </value></part><part><name>See Also</name>=<value>\n</value></part></template>\n\n&lt;dl class=\"command_description\"&gt;\n<comment>&lt;!-- BEGIN Note Section --&gt;\n</comment>\n<comment>&lt;!-- END Note Section --&gt;\n</comment>&lt;/dl&gt;\n\n&lt;h3 style=\"display:none\"&gt;Bottom Section&lt;/h3&gt;</root>"}}}